pybindingcurve/__init__.py
pybindingcurve/pybindingcurve.py
pybindingcurve/systems/__init__.py
pybindingcurve/systems/analytical_equations.py
pybindingcurve/systems/analytical_systems.py
pybindingcurve/systems/binding_system.py
pybindingcurve/systems/kinetic_systems.py
pybindingcurve/systems/kinetic_systems_1_to_1to5.py
pybindingcurve/systems/lagrange_binding_system_factory.py
pybindingcurve/systems/lagrange_systems.py
pybindingcurve/systems/minimizer_binding_system_factory.py
pybindingcurve/systems/minimizer_systems.py
pybindingcurve/systems/systems.py
pybindingcurve-1.2.3.dist-info/LICENSE
pybindingcurve-1.2.3.dist-info/METADATA
pybindingcurve-1.2.3.dist-info/WHEEL
pybindingcurve-1.2.3.dist-info/top_level.txt
pybindingcurve-1.2.3.dist-info/RECORD
