Metadata-Version: 2.1
Name: pybindingcurve
Version: 1.2.3
Summary: Protein ligand binding simulation in Python
Author: Steven Shave
Project-URL: Homepage, https://github.com/stevenshave/pybindingcurve
Keywords: molecular similarity,ligand based virtual screening
Requires-Python: >=3.9
License-File: LICENSE
Requires-Dist: numpy >=1.26
Requires-Dist: matplotlib >=3.8
Requires-Dist: lmfit >=1.2.2
Requires-Dist: mpmath >=1.3.0
Requires-Dist: autograd >=1.6.2
Provides-Extra: dev
Requires-Dist: black ==24.3.0 ; extra == 'dev'
Requires-Dist: pytest ==8.1.1 ; extra == 'dev'
Requires-Dist: build ==0.10.0 ; extra == 'dev'
